infer_types/__init__.py
infer_types/__main__.py
infer_types/_cli.py
infer_types/_constants.py
infer_types/_extractors.py
infer_types/_format.py
infer_types/_fsig.py
infer_types/_inferno.py
infer_types/_transformer.py
infer_types/py.typed
infer_types-1.0.0.dist-info/LICENSE
infer_types-1.0.0.dist-info/WHEEL
infer_types-1.0.0.dist-info/METADATA
infer_types-1.0.0.dist-info/RECORD
